steamapex.py
steamapex-1.0.0.dist-info/METADATA
steamapex-1.0.0.dist-info/WHEEL
steamapex-1.0.0.dist-info/entry_points.txt
steamapex-1.0.0.dist-info/top_level.txt
steamapex-1.0.0.dist-info/RECORD
