Metadata-Version: 2.1
Name: steamapex
Version: 1.0.0
Summary: show Apex on steam
Home-page: https://github.com/ousyouyou/steamapex
Author: ousyouyou
Author-email: s2122011@stu.musashino-u.ac.jp
Project-URL: Bug Tracker, https://github.com/ousyouyou/steamapex
Classifier: Programming Language :: Python :: 3
Classifier: License :: OSI Approved :: MIT License
Classifier: Operating System :: OS Independent
Requires-Python: >=3.7
